[{"name":"Alfred Hitchcock"},
 {"name":"Barry Levinson"},
 {"name":"Bernard Rose"},
 {"name":"Brian De Palmas"},
 {"name":"Bryan Singer"},
 {"name":"Chris Columbus"},
 {"name":"D`Urville Martin"},
 {"name":"David Anspaugh"},
 {"name":"David Fincher"},
 {"name":"David Lynch"},
 {"name":"Francis Ford Coppola"},
 {"name":"Frank Darabont"},
 {"name":"George Lucas"},
 {"name":"George Tillman"},
 {"name":"Gus Van Sant"},
 {"name":"Harold Becker"},
 {"name":"Harold Ramis"},
 {"name":"J. Robert Wagoner"},
 {"name":"James Cameron"},
 {"name":"Jay Roach"},
 {"name":"Jeremiah Chechik"},
 {"name":"Jerry Zucker"},
 {"name":"John Boorman"},
 {"name":"John Landis"},
 {"name":"John McTiernan"},
 {"name":"John Schlesinger"},
 {"name":"John Singleton"},
 {"name":"Johnathan Frakes"},
 {"name":"Jonathan Demme"},
 {"name":"Mary Lambert"},
 {"name":"Mel Gibson"},
 {"name":"Michael Bay"},
 {"name":"Michael Schultz"},
 {"name":"Mimi Leder"},
 {"name":"Peter Farrelly"},
 {"name":"Ridley Scott"},
 {"name":"Rob Reiner"},
 {"name":"Robert Zemeckis"},
 {"name":"Roland Emmerich"},
 {"name":"Sean S. Cunningham"},
 {"name":"Spike Lee"},
 {"name":"Stanley Kubrick"},
 {"name":"Steven Lisberger"},
 {"name":"Steven Spielberg"},
 {"name":"Sydney Pollack"},
 {"name":"Terry Gilliam"},
 {"name":"Tobe Hopper"},
 {"name":"Tom Shadyac"},
 {"name":"Tony Scott"},
 {"name":"Victor Fleming"},
 {"name":"Wes Craven"}]